pdf_reader/__init__.py
pdf_reader/converter.py
pdf_reader/custom_dataclasses.py
pdf_reader/extract.py
pdf_reader/helper.py
pdf_reader/pdf_page.py
pdf_reader/visualisation.py
parsee_pdf_reader-0.1.8.2.dist-info/LICENSE
parsee_pdf_reader-0.1.8.2.dist-info/METADATA
parsee_pdf_reader-0.1.8.2.dist-info/WHEEL
parsee_pdf_reader-0.1.8.2.dist-info/RECORD
